spotipy_random/__init__.py
spotipy_random/spotipy_random.py
spotipy_random-0.0.3.dist-info/LICENSE
spotipy_random-0.0.3.dist-info/METADATA
spotipy_random-0.0.3.dist-info/WHEEL
spotipy_random-0.0.3.dist-info/top_level.txt
spotipy_random-0.0.3.dist-info/RECORD
