Metadata-Version: 2.1
Name: spotipy-random
Version: 0.0.3
Summary: Extends the spotipy API client with randomized search.
Home-page: https://github.com/michimalek/spotipy-random
Author: Michael Malek, Lennard Beers
Author-email: michimalek00@gmail.com, l.beers@outlook.de
License: UNKNOWN
Project-URL: Bug Tracker, https://github.com/michimalek/spotipy-random/issues
Platform: UNKNOWN
Classifier: Programming Language :: Python :: 3
Classifier: License :: OSI Approved :: MIT License
Classifier: Operating System :: OS Independent
Requires-Python: >=3.6
License-File: LICENSE
